{
  "entries": {
    "actions/cache/restore@v5.0.4": {
      "repo": "actions/cache/restore",
      "version": "v5.0.4",
      "sha": "668228422ae6a00e4ad889ee87cd7109ec5666a7"
    },
    "actions/cache/save@v5.0.4": {
      "repo": "actions/cache/save",
      "version": "v5.0.4",
      "sha": "668228422ae6a00e4ad889ee87cd7109ec5666a7"
    },
    "actions/checkout@v6.0.2": {
      "repo": "actions/checkout",
      "version": "v6.0.2",
      "sha": "de0fac2e4500dabe0009e67214ff5f5447ce83dd"
    },
    "actions/create-github-app-token@v3.0.0": {
      "repo": "actions/create-github-app-token",
      "version": "v3.0.0",
      "sha": "f8d387b68d61c58ab83c6c016672934102569859"
    },
    "actions/download-artifact@v8.0.1": {
      "repo": "actions/download-artifact",
      "version": "v8.0.1",
      "sha": "3e5f45b2cfb9172054b4087a40e8e0b5a5461e7c"
    },
    "actions/github-script@v8": {
      "repo": "actions/github-script",
      "version": "v8",
      "sha": "ed597411d8f924073f98dfc5c65a23a2325f34cd"
    },
    "actions/setup-go@v6.4.0": {
      "repo": "actions/setup-go",
      "version": "v6.4.0",
      "sha": "4a3601121dd01d1626a1e23e37211e3254c1c06c"
    },
    "actions/setup-node@v6.3.0": {
      "repo": "actions/setup-node",
      "version": "v6.3.0",
      "sha": "53b83947a5a98c8d113130e565377fae1a50d02f"
    },
    "actions/upload-artifact@v7": {
      "repo": "actions/upload-artifact",
      "version": "v7",
      "sha": "043fb46d1a93c77aae656e7c1c64a875d1fc6a0a"
    },
    "actions/upload-artifact@v7.0.0": {
      "repo": "actions/upload-artifact",
      "version": "v7.0.0",
      "sha": "bbbca2ddaa5d8feaa63e36b76fdaad77386f024f"
    },
    "anchore/sbom-action@v0.24.0": {
      "repo": "anchore/sbom-action",
      "version": "v0.24.0",
      "sha": "e22c389904149dbc22b58101806040fa8d37a610"
    },
    "docker/build-push-action@v7.0.0": {
      "repo": "docker/build-push-action",
      "version": "v7.0.0",
      "sha": "d08e5c354a6adb9ed34480a06d141179aa583294"
    },
    "docker/login-action@v4.1.0": {
      "repo": "docker/login-action",
      "version": "v4.1.0",
      "sha": "4907a6ddec9925e35a0a9e82d7399ccc52663121"
    },
    "docker/metadata-action@v6.0.0": {
      "repo": "docker/metadata-action",
      "version": "v6.0.0",
      "sha": "030e881283bb7a6894de51c315a6bfe6a94e05cf"
    },
    "docker/setup-buildx-action@v4.0.0": {
      "repo": "docker/setup-buildx-action",
      "version": "v4.0.0",
      "sha": "4d04d5d9486b7bd6fa91e7baf45bbb4f8b9deedd"
    },
    "github/gh-aw-actions/setup-cli@v0.67.4": {
      "repo": "github/gh-aw-actions/setup-cli",
      "version": "v0.67.4",
      "sha": "9d6ae06250fc0ec536a0e5f35de313b35bad7246"
    },
    "github/gh-aw-actions/setup@v0.67.0": {
      "repo": "github/gh-aw-actions/setup",
      "version": "v0.67.0",
      "sha": "cde65c546c2b0f6d3f3a9492a04e6687887c4fe8"
    },
    "github/gh-aw-actions/setup@v0.67.4": {
      "repo": "github/gh-aw-actions/setup",
      "version": "v0.67.4",
      "sha": "9d6ae06250fc0ec536a0e5f35de313b35bad7246"
    },
    "github/gh-aw/actions/setup@v0.67.4": {
      "repo": "github/gh-aw/actions/setup",
      "version": "v0.67.4",
      "sha": "78323e834d6a0284641b43590d8c097d1d815d22"
    },
    "githubnext/gh-aw/actions/setup@v0.67.4": {
      "repo": "githubnext/gh-aw/actions/setup",
      "version": "v0.67.4",
      "sha": "78323e834d6a0284641b43590d8c097d1d815d22"
    }
  }
}
